findbyid/__init__.py
findbyid/decorator.py
findbyid-0.0.7.dist-info/LICENSE
findbyid-0.0.7.dist-info/METADATA
findbyid-0.0.7.dist-info/WHEEL
findbyid-0.0.7.dist-info/top_level.txt
findbyid-0.0.7.dist-info/RECORD
