Metadata-Version: 2.1
Name: findbyid
Version: 0.0.7
Summary: A package that allows any instance of a class to be referenced with its ID that is provided by this package
Home-page: https://github.com/NoSocksForYou/findbyid.git
Author: Kaappo Raivio
Author-email: kaappo.raivio@gmail.com
License: UNKNOWN
Platform: UNKNOWN
Classifier: Programming Language :: Python :: 3
Classifier: License :: OSI Approved :: MIT License
Classifier: Operating System :: OS Independent
